ipniutil/__init__.py
ipniutil/nameutil.py
ipniutil/publutil.py
ipniutil/typeutil.py
ipniutil/geoutil/__init__.py
ipniutil/geoutil/dist2iso.py
ipniutil/geoutil/data/__init__.py
ipniutil/geoutil/data/iso_std.csv
ipniutil/geoutil/data/tdwg_l1.txt
ipniutil/geoutil/data/tdwg_l2.txt
ipniutil/geoutil/data/tdwg_l3.txt
ipniutil/geoutil/data/tdwg_l4.txt
ipniutil/geoutil/resources/__init__.py
ipniutil/geoutil/resources/tdwg-hierarchy-corrections.txt
ipniutil-0.0.21.dist-info/METADATA
ipniutil-0.0.21.dist-info/WHEEL
ipniutil-0.0.21.dist-info/top_level.txt
ipniutil-0.0.21.dist-info/RECORD
