Metadata-Version: 2.1
Name: ipniutil
Version: 0.0.21
Summary: Utilities package for working with IPNI data
Home-page: https://github.com/nickynicolson/ipniutil
Author: Nicky Nicolson
Author-email: n.nicolson@kew.org
License: UNKNOWN
Project-URL: Bug Tracker, https://github.com/nickynicolson/ipniutil/issues
Platform: UNKNOWN
Classifier: Programming Language :: Python :: 3
Classifier: License :: OSI Approved :: MIT License
Classifier: Operating System :: OS Independent
Requires-Python: >=3.6
Requires-Dist: pandas
Requires-Dist: unidecode
